README.txt
setup.py
collective/__init__.py
collective.alertviewlet.egg-info/PKG-INFO
collective.alertviewlet.egg-info/SOURCES.txt
collective.alertviewlet.egg-info/dependency_links.txt
collective.alertviewlet.egg-info/entry_points.txt
collective.alertviewlet.egg-info/namespace_packages.txt
collective.alertviewlet.egg-info/not-zip-safe
collective.alertviewlet.egg-info/requires.txt
collective.alertviewlet.egg-info/top_level.txt
collective/alertviewlet/__init__.py
collective/alertviewlet/configure.zcml
collective/alertviewlet/controlpanel_alert.py
collective/alertviewlet/tests.py
collective/alertviewlet/browser/__init__.py
collective/alertviewlet/browser/configure.zcml
collective/alertviewlet/browser/view.py
collective/alertviewlet/browser/templates/alert.pt
collective/alertviewlet/profiles/default/actionicons.xml
collective/alertviewlet/profiles/default/controlpanel.xml
collective/alertviewlet/profiles/default/metadata.xml
collective/alertviewlet/profiles/default/propertiestool.xml
collective/alertviewlet/profiles/default/viewlets.xml
docs/HISTORY.txt
docs/INSTALL.txt
docs/LICENSE.GPL
docs/LICENSE.txt