Metadata-Version: 1.0
Name: collective.alertviewlet
Version: 0.2
Summary: Allows site administrator to quickly put a global alert on the site
Home-page: http://svn.plone.org/collective/collective.alertviewlet
Author: Antonio Tirabasso; Francesco Merlo
Author-email: antonio.tirabasso@reflab.it; francesco.merlo@reflab.it
License: GPL
Platform: UNKNOWN
Classifier: Framework :: Plone
Classifier: Programming Language :: Python
Classifier: Topic :: Software Development :: Libraries :: Python Modules
